soldier/__init__.py
soldier/exceptions.py
soldier/helpers.py
soldier/soldier.py
soldier-0.2.5.dist-info/LICENSE
soldier-0.2.5.dist-info/METADATA
soldier-0.2.5.dist-info/WHEEL
soldier-0.2.5.dist-info/top_level.txt
soldier-0.2.5.dist-info/RECORD
