Metadata-Version: 2.1
Name: soldier
Version: 0.2.5
Summary: Subprocess with Style
Home-page: https://pypi.python.org/pypi/soldier
Author: Yash Mehrotra
Author-email: yashmehrotra95@gmail.com
License: Apache 2.0
Platform: UNKNOWN
